setup.py
salom/__init__.py
salom.egg-info/PKG-INFO
salom.egg-info/SOURCES.txt
salom.egg-info/dependency_links.txt
salom.egg-info/top_level.txt