Metadata-Version: 1.0
Name: salom
Version: 0.0.1
Summary: Salom!!
Home-page: https://turgunov.uz/
Author: Shukrullo Turgunov
Author-email: shookrullo@gmail.com
License: UNKNOWN
Keywords: pip,pypi
Platform: UNKNOWN
